make.py
setup.py
docs/html/genindex.html
docs/html/index.html
docs/html/modindex.html
docs/html/search.html
docs/html/searchindex.json
docs/html/.doctrees/environment.pickle
docs/html/.doctrees/index.doctree
docs/html/_sources/index.txt
docs/html/_static/contents.png
docs/html/_static/default.css
docs/html/_static/doctools.js
docs/html/_static/file.png
docs/html/_static/interface.js
docs/html/_static/jquery.js
docs/html/_static/minus.png
docs/html/_static/navigation.png
docs/html/_static/plus.png
docs/html/_static/pygments.css
docs/html/_static/rightsidebar.css
docs/html/_static/searchtools.js
docs/html/_static/sphinxdoc.css
docs/html/_static/stickysidebar.css
docs/html/_static/traditional.css
docs/source/conf.py
docs/source/index.rst
src/pyjld/__init__.py
src/pyjld.system.egg-info/PKG-INFO
src/pyjld.system.egg-info/SOURCES.txt
src/pyjld.system.egg-info/dependency_links.txt
src/pyjld.system.egg-info/namespace_packages.txt
src/pyjld.system.egg-info/requires.txt
src/pyjld.system.egg-info/top_level.txt
src/pyjld.system.egg-info/zip-safe
src/pyjld/system/__init__.py
src/pyjld/system/proxy.py
src/pyjld/system/command/__init__.py
src/pyjld/system/command/base.py
src/pyjld/system/command/ui.py
src/pyjld/system/command/tests/tests.py
src/pyjld/system/command/tests/tests.txt
src/pyjld/system/daemon/__init__.py
src/pyjld/system/daemon/base.py
src/pyjld/system/daemon/helper.py
src/pyjld/system/daemon/tests/test.py
src/pyjld/system/registry/__init__.py
src/pyjld/system/registry/base.py
src/pyjld/system/registry/reg_linux.py
src/pyjld/system/registry/reg_windows.py
src/pyjld/system/registry/tests/tests.py
src/pyjld/system/registry/tests/tests.txt
tests/tests.py