Metadata-Version: 1.0
Name: pyjld.system
Version: 0.4
Summary: pyjld.system: various system level utilities (e.g. daemon, cross-platform registry, command-line tools)
Home-page: http://pyjld.googlecode.com/svn/trunk/pyjld.system/tags/0.4/docs/index.html
Author: Jean-Lou Dupont
Author-email: python (at) jldupont.com
License: UNKNOWN
Platform: UNKNOWN
Classifier: Development Status :: 4 - Beta
Classifier: Intended Audience :: Developers
Classifier: License :: Public Domain
Classifier: Programming Language :: Python
Classifier: Topic :: Software Development :: Libraries :: Python Modules
Classifier: Operating System :: Microsoft :: Windows
Classifier: Operating System :: POSIX
